Workbook

Sheet Company Baseline
A1: COMPANY BASELINE - CURRENT STATE METRICS
A3: Instructions: Modify the YELLOW cells to change baseline assumptions. All other sheets reference these values.
A5: FINANCIAL METRICS
A6: Metric | B6: Value | C6: Unit | D6: Notes
A7: Annual Revenue | B7: 527000000 | C7: USD | D7: FY2024 total revenue
A8: Gross Margin % | B8: 0.35 | C8: % | D8: 35% gross margin
A9: Net Margin % | B9: 0.07 | C9: % | D9: 7% net margin
A10: Gross Profit | B10: =B7*B8 | C10: USD | D10: =Revenue × Gross Margin
A11: Net Income | B11: =B7*B9 | C11: USD | D11: =Revenue × Net Margin
A13: OPERATIONAL METRICS
A14: Metric | B14: Value | C14: Unit | D14: Notes
A15: Annual Projects Completed | B15: 2100 | C15: # | D15: Projects delivered per year
A16: Annual Bids Submitted | B16: 11700 | C16: # | D16: Total bids per year
A17: Current Win Rate | B17: =B15/B16 | C17: % | D17: =Projects / Bids
A18: Average Project Value | B18: 250000 | C18: USD | D18: Average commercial roofing project
A19: Average Project Duration | B19: 45 | C19: days | D19: Average project timeline
A20: Daily Revenue per Project | B20: =B18/B19 | C20: USD | D20: =Avg Project Value / Duration
A22: WORKFORCE METRICS
A23: Metric | B23: Value | C23: Unit | D23: Notes
A24: Estimators | B24: 25 | C24: # | D24: Full-time estimating staff
A25: Project Managers | B25: 45 | C25: # | D25: Full-time PM staff
A26: Sales Representatives | B26: 30 | C26: # | D26: Full-time sales staff
A27: Hourly Labor Cost (Loaded) | B27: 75 | C27: USD/hr | D27: Fully loaded labor cost
A28: Working Hours per Year | B28: 2080 | C28: hrs | D28: Standard annual hours

Sheet Platform 0
A1: PLATFORM 0: AI MARKET EXPANSION ENGINE
A2: Autonomous Agent Swarm for Lead Generation and Sales Acceleration
A3: Instructions: Modify YELLOW input cells to see how changes affect calculated results (GREEN cells).
A5: INPUT PARAMETERS
A6: Parameter | B6: Value | C6: Unit | D6: Description
A7: Annual Leads Generated | B7: 10000 | C7: # | D7: Target leads from AI agent swarm
A8: Lead-to-Meeting Conversion Rate | B8: 0.12 | C8: % | D8: 12% of leads become meetings
A9: Meeting-to-Close Rate | B9: 0.2 | C9: % | D9: 20% of meetings become projects
A10: Cost Per Lead (AI) | B10: 120 | C10: USD | D10: Reduced from $350 baseline
A11: Cost Per Lead (Baseline) | B11: 350 | C11: USD | D11: Current cost per lead
A12: Maintenance Plan Attach Rate | B12: 0.25 | C12: % | D12: 25% of new projects add maintenance
A13: Maintenance Plan Annual Value | B13: 25000 | C13: USD | D13: Average annual maintenance contract
A14: Sales Cycle Reduction (Days) | B14: 14 | C14: days | D14: Days saved in sales cycle
A16: CALCULATED KPIs (Formulas Reference Inputs Above)
A17: KPI | B17: Formula | C17: Result | D17: Unit
A18: Qualified Meetings | B18: Leads × Lead-to-Meeting Rate | C18: =B7*B8 | D18: %
A19: New Projects Won | B19: Meetings × Meeting-to-Close Rate | C19: =C18*B9 | D19: #
A20: Gross Revenue from New Projects | B20: Projects × Avg Project Value | C20: =C19*'Company Baseline'!B18 | D20: USD
A21: Net Revenue Contribution | B21: Gross Revenue × Net Margin | C21: =C20*'Company Baseline'!B9 | D21: USD
A22: Maintenance Contracts Sold | B22: Projects × Attach Rate | C22: =C19*B12 | D22: #
A23: Maintenance Revenue | B23: Contracts × Annual Value | C23: =C22*B13 | D23: USD
A24: Lead Cost Savings | B24: (Baseline CPL - AI CPL) × Leads | C24: =(B11-B10)*B7 | D24: USD
A25: Cash Flow Acceleration | B25: Projects × Days Saved × Daily Rev | C25: =C19*B14*'Company Baseline'!B20 | D25: USD
A27: FINANCIAL IMPACT SUMMARY
A28: Benefit Category | B28: Formula Reference | C28: Annual Value
A29: Revenue Growth - New Projects | B29: =Net Revenue Contribution (C21) | C29: =C21
A30: Revenue Growth - Maintenance | B30: =Maintenance Revenue (C23) | C30: =C23
A31: Cost Reduction - Lead Savings | B31: =Lead Cost Savings (C24) | C31: =C24
A32: Cash Flow - Acceleration | B32: =Cash Flow Acceleration (C25) | C32: =C25
A33: Risk Mitigation (Estimated) | B33: 5% of revenue growth | C33: 500000
A34: TOTAL PLATFORM 0 BENEFIT | B34: =SUM of above | C34: =SUM(C29:C33)
A36: INVESTMENT & ROI ANALYSIS
A37: Metric | B37: Value | C37: Notes
A38: Platform Development Cost | B38: 1200000 | C38: One-time investment
A39: Annual Data Subscription | B39: 410000 | C39: Ongoing annual cost
A40: Total Year 1 Investment | B40: =B38+B39 | C40: Development + First Year Data
A41: Annual Benefit (from above) | B41: =C34 | C41: Total Platform 0 Benefit
A42: Net Year 1 Benefit | B42: =B41-B40 | C42: Benefit minus Investment
A43: Year 1 ROI | B43: =(B41-B40)/B40 | C43: Net Benefit / Investment
A44: Payback Period (Months) | B44: =B40/B41*12 | C44: Investment / Monthly Benefit

Sheet Platform 1
A1: PLATFORM 1: AI SALES INTELLIGENCE
A2: Intelligent Bid Selection and Competitive Analysis
A3: Instructions: Modify YELLOW input cells to see how changes affect calculated results (GREEN cells).
A5: INPUT PARAMETERS
A6: Parameter | B6: Value | C6: Unit | D6: Description
A7: Win Rate Improvement | B7: 11 | C7: pts | D7: Percentage points (22% → 33%)
A8: Bid Evaluation Time - Current | B8: 3 | C8: hrs | D8: Hours per bid currently
A9: Bid Evaluation Time - With AI | B9: 0.5 | C9: hrs | D9: Hours per bid with AI
A10: Bid Assignment Attribution | B10: 0.55 | C10: % | D10: 55% of improvement from bid assignment
A11: Competitor Analysis Attribution | B11: 0.27 | C11: % | D11: 27% from competitor analysis
A12: Competitor Scouting Attribution | B12: 0.18 | C12: % | D12: 18% from competitor scouting
A14: CALCULATED KPIs
A15: KPI | B15: Formula Description | C15: Result | D15: Unit
A16: Current Win Rate | B16: From Company Baseline | C16: ='Company Baseline'!B17 | D16: %
A17: New Win Rate | B17: Current + Improvement pts | C17: =C16+B7/100 | D17: %
A18: Additional Wins per Year | B18: Bids × Improvement % | C18: ='Company Baseline'!B16*B7/100 | D18: #
A19: Time Saved per Bid (hrs) | B19: Current - AI Time | C19: =B8-B9 | D19: hrs
A20: Total Hours Saved per Year | B20: Bids × Hours Saved | C20: ='Company Baseline'!B16*C19 | D20: hrs
A21: Revenue per Additional Win | B21: Avg Project × Gross Margin | C21: ='Company Baseline'!B18*'Company Baseline'!B8 | D21: USD
A22: Total Revenue from Wins | B22: Additional Wins × Revenue Each | C22: =C18*C21 | D22: USD
A23: Labor Cost Savings | B23: Hours Saved × Hourly Rate | C23: =C20*'Company Baseline'!B27 | D23: USD
A25: USE CASE FINANCIAL BREAKDOWN
A26: Use Case | B26: Attribution % | C26: Revenue Impact | D26: Labor Savings | E26: Total
A27: Bid Assignment AI | B27: =B10 | C27: =C22*B10 | D27: =C23*0.3 | E27: =C27+D27
A28: Competitor Proposal Analysis | B28: =B11 | C28: =C22*B11 | D28: =C23*0.33 | E28: =C28+D28
A29: Competitor Info Scouting | B29: =B12 | C29: =C22*B12 | D29: =C23*0.37 | E29: =C29+D29
A30: TOTAL PLATFORM 1 BENEFIT | B30: 100% | C30: =SUM(C27:C29) | D30: =SUM(D27:D29) | E30: =SUM(E27:E29)

Sheet Platform 2
A1: PLATFORM 2: AI ESTIMATION SUITE
A2: Automated Proposal Creation and Specification Analysis
A3: Instructions: Modify YELLOW input cells. GREEN cells calculate automatically.
A5: INPUT PARAMETERS
A6: Parameter | B6: Current | C6: With AI | D6: Improvement | E6: Unit
A7: Proposal Creation Time | B7: 2.5 | C7: 0.33 | D7: =1-C7/B7 | E7: hrs
A8: Spec Review Time | B8: 3 | C8: 0.5 | D8: =1-C8/B8 | E8: hrs
A9: Estimate Error Rate | B9: 0.08 | C9: 0.02 | D9: =1-C9/B9 | E9: %
A10: Technical QA Time | B10: 4 | C10: 0.25 | D10: =1-C10/B10 | E10: hrs
A11: Proposals per Year | B11: 11700 | C11: 11700 | D11: N/A | E11: #
A13: USE CASE FINANCIAL BREAKDOWN
A14: Use Case | B14: Hours Saved | C14: Labor Savings | D14: Revenue Impact | E14: Risk Reduction | F14: Total
A15: Proposal Creation | B15: =(B7-C7)*B11 | C15: =B15*'Company Baseline'!B27 | D15: 4585000 | E15: 0 | F15: =C15+D15+E15
A16: Specification Reviews | B16: =(B8-C8)*B11 | C16: =B16*'Company Baseline'!B27 | D16: 3780000 | E16: 700000 | F16: =C16+D16+E16
A17: Edge Estimate Reviews | B17: =B11*0.5 | C17: =B17*'Company Baseline'!B27 | D17: 4095000 | E17: 0 | F17: =C17+D17+E17
A18: Compare Quotes to Specs | B18: =B11*0.3 | C18: =B18*'Company Baseline'!B27 | D18: 0 | E18: 3240000 | F18: =C18+D18+E18
A19: Proposal Evaluation | B19: =B11*0.2 | C19: =B19*'Company Baseline'!B27 | D19: 1838000 | E19: 0 | F19: =C19+D19+E19
A20: Technical Questions | B20: =(B10-C10)*B11 | C20: =B20*'Company Baseline'!B27 | D20: 455000 | E20: 0 | F20: =C20+D20+E20
A21: TOTAL PLATFORM 2 BENEFIT | B21: =SUM(B15:B20) | C21: =SUM(C15:C20) | D21: =SUM(D15:D20) | E21: =SUM(E15:E20) | F21: =SUM(F15:F20)

Sheet Platform 3
A1: PLATFORM 3: AI PROJECT MANAGEMENT
A2: Seamless Project Delivery and Customer Experience
A3: Instructions: Modify YELLOW input cells. GREEN cells calculate automatically.
A5: INPUT PARAMETERS
A6: Parameter | B6: Current | C6: With AI | D6: Improvement | E6: Unit
A7: Schedule Creation Time | B7: 10 | C7: 2.5 | D7: =1-C7/B7 | E7: hrs
A8: Project Delay (avg) | B8: 12 | C8: 3 | D8: =1-C8/B8 | E8: days
A9: Variance Detection Time | B9: 30 | C9: 1 | D9: =1-C9/B9 | E9: days
A10: Closeout Assembly Time | B10: 2 | C10: 0.5 | D10: =1-C10/B10 | E10: hrs
A11: Report Creation Time | B11: 45 | C11: 5 | D11: =1-C11/B11 | E11: min
A12: Projects per Year | B12: 2100 | C12: 2100 | D12: N/A | E12: #
A14: USE CASE FINANCIAL BREAKDOWN (Document Verified Values)
A15: Use Case | B15: Labor Savings | C15: Cost Reduction | D15: Revenue Impact | E15: Cash Flow | F15: Total
A16: Schedule Generation | B16: 94000 | C16: 9450000 | D16: 0 | E16: 0 | F16: =SUM(B16:E16)
A17: BU Actual vs Estimate | B17: 107000 | C17: 2025000 | D17: 735000 | E17: 0 | F17: =SUM(B17:E17)
A18: RFI Response Generation | B18: 284000 | C18: 1563000 | D18: 0 | E18: 0 | F18: =SUM(B18:E18)
A19: Project Closeout Docs | B19: 202000 | C19: 150000 | D19: 0 | E19: 445000 | F19: =SUM(B19:E19)
A20: Daily/Weekly Reports | B20: 580000 | C20: 0 | D20: 0 | E20: 0 | F20: =SUM(B20:E20)
A21: Pre-Con Packets + Portfolio | B21: 700000 | C21: 0 | D21: 2000000 | E21: 750000 | F21: =SUM(B21:E21)
A22: TOTAL PLATFORM 3 BENEFIT | B22: =SUM(B16:B21) | C22: =SUM(C16:C21) | D22: =SUM(D16:D21) | E22: =SUM(E16:E21) | F22: =SUM(F16:F21)

Sheet Platform 4
A1: PLATFORM 4: AI KNOWLEDGE MANAGEMENT
A2: Foundation Layer with RBAC and Data Classification
A3: Instructions: Modify YELLOW input cells. GREEN cells calculate automatically.
A5: INPUT PARAMETERS
A6: Parameter | B6: Current | C6: With AI | D6: Improvement | E6: Unit
A7: Submittal Assembly Time | B7: 13.5 | C7: 2 | D7: =1-C7/B7 | E7: hrs
A8: Completeness Rate | B8: 0.88 | C8: 0.99 | D8: =(C8-B8)/B8 | E8: %
A9: Spec-to-Edge Mapping Accuracy | B9: 0.75 | C9: 0.95 | D9: =(C9-B9)/B9 | E9: %
A10: Submittals per Year | B10: 2100 | C10: 2100 | D10: N/A | E10: #
A12: USE CASE FINANCIAL BREAKDOWN
A13: Use Case | B13: Hours Saved | C13: Labor Savings | D13: Revenue Impact | E13: Total
A14: Submittal Package Assembly | B14: =(B7-C7)*B10 | C14: =B14*'Company Baseline'!B27 | D14: 3250000 | E14: =C14+D14
A15: Spec-to-Edge Mapping | B15: =B10*0.5 | C15: =B15*'Company Baseline'!B27 | D15: 680000 | E15: =C15+D15
A16: TOTAL PLATFORM 4 BENEFIT | B16: =SUM(B14:B15) | C16: =SUM(C14:C15) | D16: =SUM(D14:D15) | E16: =SUM(E14:E15)

Sheet Consolidated
A1: CONSOLIDATED FINANCIAL SUMMARY
A3: All values below are calculated from the individual platform sheets. Change inputs there to see updates here.
A5: ANNUAL BENEFIT BY PLATFORM
A6: Platform | B6: Total Benefit | C6: % of Total
A7: P0: AI Market Expansion Engine | B7: ='Platform 0'!C34 | C7: =B7/$B$12
A8: P1: AI Sales Intelligence | B8: ='Platform 1'!E30 | C8: =B8/$B$12
A9: P2: AI Estimation Suite | B9: ='Platform 2'!F21 | C9: =B9/$B$12
A10: P3: AI Project Management | B10: ='Platform 3'!F22 | C10: =B10/$B$12
A11: P4: AI Knowledge Management | B11: ='Platform 4'!E16 | C11: =B11/$B$12
A12: GRAND TOTAL ANNUAL BENEFIT | B12: =SUM(B7:B11) | C12: 100%
A14: POST-TRANSFORMATION METRICS
A15: Metric | B15: Current | C15: Post-Transform | D15: Change | E15: % Change
A16: Annual Revenue | B16: ='Company Baseline'!B7 | C16: 603000000 | D16: =C16-B16 | E16: =(C16-B16)/B16
A17: Win Rate | B17: ='Company Baseline'!B17 | C17: 0.33 | D17: =C17-B17 | E17: =(C17-B17)/B17
A18: Net Income | B18: ='Company Baseline'!B11 | C18: 147500000 | D18: =C18-B18 | E18: =(C18-B18)/B18
A19: Annual Projects | B19: ='Company Baseline'!B15 | C19: 3600 | D19: =C19-B19 | E19: =(C19-B19)/B19
A21: TOTAL INVESTMENT SUMMARY
A22: Category | B22: Amount
A23: Platform Development (One-Time) | B23: 4500000
A24: Annual Operating Costs | B24: 1200000
A25: Total Year 1 Investment | B25: =B23+B24
A26: Annual Benefit | B26: =B12
A27: Net Year 1 Benefit | B27: =B26-B25
A28: Overall ROI | B28: =(B26-B25)/B25

Sheet Scenario Builder
A1: SCENARIO BUILDER
A2: Create custom scenarios by modifying the yellow cells below. Compare against the base case.
A4: SCENARIO PARAMETERS
A5: Parameter | B5: Base Case | C5: Your Scenario | D5: Difference | E5: % Change
A6: Annual Leads (P0) | B6: 10000 | C6: 10000 | D6: =C6-B6 | E6: =IF(B6=0,0,(C6-B6)/B6)
A7: Lead-to-Meeting Rate (P0) | B7: 0.12 | C7: 0.12 | D7: =C7-B7 | E7: =IF(B7=0,0,(C7-B7)/B7)
A8: Meeting-to-Close Rate (P0) | B8: 0.2 | C8: 0.2 | D8: =C8-B8 | E8: =IF(B8=0,0,(C8-B8)/B8)
A9: Win Rate Improvement pts (P1) | B9: 11 | C9: 11 | D9: =C9-B9 | E9: =IF(B9=0,0,(C9-B9)/B9)
A10: Annual Bids | B10: 11700 | C10: 11700 | D10: =C10-B10 | E10: =IF(B10=0,0,(C10-B10)/B10)
A11: Average Project Value | B11: 250000 | C11: 250000 | D11: =C11-B11 | E11: =IF(B11=0,0,(C11-B11)/B11)
A12: Gross Margin | B12: 0.35 | C12: 0.35 | D12: =C12-B12 | E12: =IF(B12=0,0,(C12-B12)/B12)
A13: Net Margin | B13: 0.07 | C13: 0.07 | D13: =C13-B13 | E13: =IF(B13=0,0,(C13-B13)/B13)
A15: SCENARIO IMPACT CALCULATIONS
A16: Metric | B16: Base Case | C16: Your Scenario | D16: Difference
A17: Platform 0 Impact:
A18: Qualified Meetings | B18: =B6*B7 | C18: =C6*C7 | D18: =C18-B18
A19: New Projects | B19: =B18*B8 | C19: =C18*C8 | D19: =C19-B19
A20: Gross Revenue | B20: =B19*B11 | C20: =C19*C11 | D20: =C20-B20
A21: Net Revenue Impact | B21: =B20*B13 | C21: =C20*C13 | D21: =C21-B21
A23: Platform 1 Impact:
A24: New Win Rate | B24: =0.22+B9/100 | C24: =0.22+C9/100 | D24: =C24-B24
A25: Additional Wins | B25: =B10*B9/100 | C25: =C10*C9/100 | D25: =C25-B25
A26: Revenue Impact | B26: =B25*B11*B12 | C26: =C25*C11*C12 | D26: =C26-B26
A28: COMBINED SCENARIO IMPACT
A29: Total Revenue Impact | B29: =B21+B26 | C29: =C21+C26 | D29: =C29-B29

Sheet Sensitivity Analysis
A1: SENSITIVITY ANALYSIS
A2: See how changes in key variables affect total benefits. Base case is highlighted.
A4: WIN RATE IMPROVEMENT SENSITIVITY
A5: Improvement (pts) | B5: Additional Wins | C5: Revenue Impact | D5: vs Base Case
A6: 5 | B6: ='Company Baseline'!B16*A6/100 | C6: =B6*'Company Baseline'!B18*'Company Baseline'!B8 | D6: =C6-$C$9
A7: 7 | B7: ='Company Baseline'!B16*A7/100 | C7: =B7*'Company Baseline'!B18*'Company Baseline'!B8 | D7: =C7-$C$9
A8: 9 | B8: ='Company Baseline'!B16*A8/100 | C8: =B8*'Company Baseline'!B18*'Company Baseline'!B8 | D8: =C8-$C$9
A9: 11 | B9: ='Company Baseline'!B16*A9/100 | C9: =B9*'Company Baseline'!B18*'Company Baseline'!B8 | D9: =C9-$C$9
A10: 13 | B10: ='Company Baseline'!B16*A10/100 | C10: =B10*'Company Baseline'!B18*'Company Baseline'!B8 | D10: =C10-$C$9
A11: 15 | B11: ='Company Baseline'!B16*A11/100 | C11: =B11*'Company Baseline'!B18*'Company Baseline'!B8 | D11: =C11-$C$9
A12: 17 | B12: ='Company Baseline'!B16*A12/100 | C12: =B12*'Company Baseline'!B18*'Company Baseline'!B8 | D12: =C12-$C$9
A14: LEAD VOLUME SENSITIVITY (P0)
A15: Annual Leads | B15: Meetings | C15: New Projects | D15: Gross Revenue
A16: 5000 | B16: =A16*0.12 | C16: =B16*0.20 | D16: =C16*'Company Baseline'!B18
A17: 7500 | B17: =A17*0.12 | C17: =B17*0.20 | D17: =C17*'Company Baseline'!B18
A18: 10000 | B18: =A18*0.12 | C18: =B18*0.20 | D18: =C18*'Company Baseline'!B18
A19: 12500 | B19: =A19*0.12 | C19: =B19*0.20 | D19: =C19*'Company Baseline'!B18
A20: 15000 | B20: =A20*0.12 | C20: =B20*0.20 | D20: =C20*'Company Baseline'!B18
A21: 17500 | B21: =A21*0.12 | C21: =B21*0.20 | D21: =C21*'Company Baseline'!B18
A22: 20000 | B22: =A22*0.12 | C22: =B22*0.20 | D22: =C22*'Company Baseline'!B18
A24: AVERAGE PROJECT VALUE SENSITIVITY
A25: Avg Project Value | B25: P0 Impact | C25: P1 Impact | D25: Combined
A26: 150000 | B26: =240*A26*0.07 | C26: =1287*A26*0.35 | D26: =B26+C26
A27: 200000 | B27: =240*A27*0.07 | C27: =1287*A27*0.35 | D27: =B27+C27
A28: 250000 | B28: =240*A28*0.07 | C28: =1287*A28*0.35 | D28: =B28+C28
A29: 300000 | B29: =240*A29*0.07 | C29: =1287*A29*0.35 | D29: =B29+C29
A30: 350000 | B30: =240*A30*0.07 | C30: =1287*A30*0.35 | D30: =B30+C30
A31: 400000 | B31: =240*A31*0.07 | C31: =1287*A31*0.35 | D31: =B31+C31
